{
  "parent": "moreboots:moreboots/ender_dragon_boots",
  "display": {
    "icon": {
      "item": "moreboots:wither_boots",
      "nbt": "{Damage:0}"
    },
    "title": {
      "translate": "advancements.moreboots.wither_boots.title"
    },
    "description": {
      "translate": "advancements.moreboots.wither_boots.description"
    },
    "frame": "task",
    "show_toast": true,
    "announce_to_chat": true,
    "hidden": false
  },
  "criteria": {
    "wither_boots": {
      "trigger": "minecraft:inventory_changed",
      "conditions": {
        "items": [
          {
            "item": "moreboots:wither_boots"
          }
        ]
      }
    }
  },
  "requirements": [
    [
      "wither_boots"
    ]
  ]
}